[{"\uc9c0\uc5ed":"\uac15\uc6d0","\uc2dc\uad70\uad6c":"\uac15\uc6d0\ub3c4 \ud6a1\uc131\uad70","\uae30\uad00":"\uc2a4\ub9c8\uc77c\uce74\uc6b4\ud2f0","\uc8fc\uc18c":"\uac15\uc6d0 \ud6a1\uc131\uad70 \uccad\uc77c\uba74 \uac11\ucc9c\ub85c 1136."},{"\uc9c0\uc5ed":"\uac15\uc6d0","\uc2dc\uad70\uad6c":"\uac15\uc6d0\ub3c4 \ud6a1\uc131\uad70","\uae30\uad00":"\ud6a1\uc131\ub178\uc778\uc8fc\uac04\ubcf4\ud638\uc13c\ud130","\uc8fc\uc18c":"\uac15\uc6d0 \ud6a1\uc131\uad70 \ud6a1\uc131\uc74d \uc5b4\uc218\ub85c 46."},{"\uc9c0\uc5ed":"\uac15\uc6d0","\uc2dc\uad70\uad6c":"\uac15\uc6d0\ub3c4 \ud6a1\uc131\uad70","\uae30\uad00":"\ub454\ub0b4\uc694\uc591\uc6d0","\uc8fc\uc18c":"\uac15\uc6d0 \ud6a1\uc131\uad70 \ub454\ub0b4\uba74 \uccad\ud0dc\uc0b0\ub85c 465-30."},{"\uc9c0\uc5ed":"\uac15\uc6d0","\uc2dc\uad70\uad6c":"\uac15\uc6d0\ub3c4 \ud6a1\uc131\uad70","\uae30\uad00":"\uc544\ub984\ub2e4\uc6b4\ub9c8\uc744","\uc8fc\uc18c":"\uac15\uc6d0 \ud6a1\uc131\uad70 \uac11\ucc9c\uba74 \uc678\uac11\ucc9c\ub85c 502-7."},{"\uc9c0\uc5ed":"\uac15\uc6d0","\uc2dc\uad70\uad6c":"\uac15\uc6d0\ub3c4 \ud6a1\uc131\uad70","\uae30\uad00":"\ud6a1\uc131\ud55c\uc6b0\ub9ac\uc694\uc591\uc6d0","\uc8fc\uc18c":"\uac15\uc6d0 \ud6a1\uc131\uad70 \ud6a1\uc131\uc74d \ud55c\uc6b0\ub85c 312."},{"\uc9c0\uc5ed":"\uac15\uc6d0","\uc2dc\uad70\uad6c":"\uac15\uc6d0\ub3c4 \ud6a1\uc131\uad70","\uae30\uad00":"\uc11c\uc6d0\uc9c0\uc5ed\uc544\ub3d9\uc13c\ud130","\uc8fc\uc18c":"\uac15\uc6d0 \ud6a1\uc131\uad70 \uc11c\uc6d0\uba74 \ucc3d\ucd0c\ub0a8\uae38 26."},{"\uc9c0\uc5ed":"\uac15\uc6d0","\uc2dc\uad70\uad6c":"\uac15\uc6d0\ub3c4 \ud6a1\uc131\uad70","\uae30\uad00":"\uc6b0\ub9ac\uc694\uc591\uc0ac\ub791\uc7ac\uac00\ubcf5\uc9c0\uc13c\ud130","\uc8fc\uc18c":"\uac15\uc6d0 \ud6a1\uc131\uad70 \ud6a1\uc131\uc74d \uc911\uc559\ub85c 14."},{"\uc9c0\uc5ed":"\uac15\uc6d0","\uc2dc\uad70\uad6c":"\uac15\uc6d0\ub3c4 \ud6a1\uc131\uad70","\uae30\uad00":"\uccad\uc77c\uc694\uc591\uc6d0","\uc8fc\uc18c":"\uac15\uc6d0\ub3c4 \ud6a1\uc131\uad70 \uccad\uc77c\uba74 \uc720\ud3c9\uae38 56-14\uccad\uc77c\uc694\uc591\uc6d0"},{"\uc9c0\uc5ed":"\uac15\uc6d0","\uc2dc\uad70\uad6c":"\uac15\uc6d0\ub3c4 \ud6a1\uc131\uad70","\uae30\uad00":"\ud6a1\uc131\ud589\ubcf5\ud55c\ud648\uc2a4\ucfe8","\uc8fc\uc18c":"\uac15\uc6d0\ub3c4 \ud6a1\uc131\uad70 \ud6a1\uc131\uc74d \ubd81\ucc9c\uc11c\ub85c20"},{"\uc9c0\uc5ed":"\uac15\uc6d0","\uc2dc\uad70\uad6c":"\uac15\uc6d0\ub3c4 \ud6a1\uc131\uad70","\uae30\uad00":"\ud6a1\uc131\uc2dc\ub2c8\uc5b4\ud074\ub7fd","\uc8fc\uc18c":"\uac15\uc6d0 \ud6a1\uc131\uad70 \ud6a1\uc131\uc74d \uc74d\ud558\ub0a8\ub85c 242\uce35"},{"\uc9c0\uc5ed":"\uac15\uc6d0","\uc2dc\uad70\uad6c":"\uac15\uc6d0\ub3c4 \ud6a1\uc131\uad70","\uae30\uad00":"\ub454\ub0b4\uc0bc\uc721\uc9c0\uc5ed\uc544\ub3d9\uc13c\ud130","\uc8fc\uc18c":"\uac15\uc6d0\ub3c4 \ud6a1\uc131\uad70 \ub454\ubc29\ub85c14\ubc88\uae38 50"},{"\uc9c0\uc5ed":"\uac15\uc6d0","\uc2dc\uad70\uad6c":"\uac15\uc6d0\ub3c4 \ud6a1\uc131\uad70","\uae30\uad00":"\ud6a1\uc131\uad70\ud55c\uc6b0\ub9ac\uc791\uc5c5\uc7a5","\uc8fc\uc18c":"\uac15\uc6d0\ub3c4 \ud6a1\uc131\uad70 \ud6a1\uc131\uc74d\ud55c\uc6b0\ub85c 223"},{"\uc9c0\uc5ed":"\uac15\uc6d0","\uc2dc\uad70\uad6c":"\uac15\uc6d0\ub3c4 \ud6a1\uc131\uad70","\uae30\uad00":"\ud6a1\uc131\uc7a5\uae30\uc694\uc591\uc13c\ud130","\uc8fc\uc18c":"\uac15\uc6d0 \ud6a1\uc131\uad70 \ud6a1\uc131\uc74d\uc74d\ud558\ub9ac 567-3"},{"\uc9c0\uc5ed":"\uac15\uc6d0","\uc2dc\uad70\uad6c":"\uac15\uc6d0\ub3c4 \ud6a1\uc131\uad70","\uae30\uad00":"\ud6a1\uc131\uc9c0\uc5ed\uc544\ub3d9\uc13c\ud130","\uc8fc\uc18c":"\uac15\uc6d0 \ud6a1\uc131\uad70 \ud6a1\uc131\uc74d\uc74d\uc0c1\ub9ac 52\ubc88\uc9c0"},{"\uc9c0\uc5ed":"\uac15\uc6d0","\uc2dc\uad70\uad6c":"\uac15\uc6d0\ub3c4 \ud6a1\uc131\uad70","\uae30\uad00":"\ud589\ubcf5\ub9c8\uc744","\uc8fc\uc18c":"\uac15\uc6d0\ub3c4 \ud6a1\uc131\uad70 \uc0c1\ud558\uac00\ub85c258\ubc88\uae38 48-10\ud589\ubcf5\ub9c8\uc744\uc694\uc591\uc6d0"},{"\uc9c0\uc5ed":"\uac15\uc6d0","\uc2dc\uad70\uad6c":"\uac15\uc6d0\ub3c4 \ud6a1\uc131\uad70","\uae30\uad00":"\ud6a1\uc131\uad70\ub2e4\ubb38\ud654\uac00\uc871\uc9c0\uc6d0\uc13c\ud130","\uc8fc\uc18c":"\uac15\uc6d0 \ud6a1\uc131\uad70 \ud6a1\uc131\uc74d \ud6a1\uc131\ub85c 379 \ud6a1\uc131\uad70\ubcf4\uac74\ubcf5\uc9c0\ud0c0\uc6b4 3\uce35"},{"\uc9c0\uc5ed":"\uac15\uc6d0","\uc2dc\uad70\uad6c":"\uac15\uc6d0\ub3c4 \ud6a1\uc131\uad70","\uae30\uad00":"\ud6a1\uc131\uad70\uc18c\uaddc\ubaa8\uc694\uc591\uc2dc\uc124","\uc8fc\uc18c":"\uac15\uc6d0\ub3c4 \ud6a1\uc131\uad70 \uc548\ud765\uba74 \uc548\ud765\ub85c 24-2\ud6a1\uc131\uad70\uc18c\uaddc\ubaa8\uc694\uc591\uc2dc\uc124"},{"\uc9c0\uc5ed":"\uac15\uc6d0","\uc2dc\uad70\uad6c":"\uac15\uc6d0\ub3c4 \ud6a1\uc131\uad70","\uae30\uad00":"\ud6a1\uc131\uad70\uc7a5\uc560\uc778\uc885\ud569\ubcf5\uc9c0\uad00","\uc8fc\uc18c":"\uac15\uc6d0\ub3c4 \ud6a1\uc131\uad70 \ud55c\uc6b0\ub85c223"},{"\uc9c0\uc5ed":"\uac15\uc6d0","\uc2dc\uad70\uad6c":"\uac15\uc6d0\ub3c4 \ud6a1\uc131\uad70","\uae30\uad00":"\ud6a1\uc131\ud6a8\ub3c4\ub9c8\uc744","\uc8fc\uc18c":"\uac15\uc6d0 \ud6a1\uc131\uad70 \uc6b0\ucc9c\uba74\uc6a9\ub454\ub9ac699\ubc88\uc9c0"},{"\uc9c0\uc5ed":"\uac15\uc6d0","\uc2dc\uad70\uad6c":"\uac15\uc6d0\ub3c4 \ud6a1\uc131\uad70","\uae30\uad00":"\ud589\ubcf5\ub9cc\ub4e4\uae30\uc0c1\ub2f4\uc18c","\uc8fc\uc18c":"\uac15\uc6d0\ub3c4 \ud6a1\uc131\uad70 \ud6a1\uc131\uc74d \ubd81\ucc9c\ub9ac 115-62"},{"\uc9c0\uc5ed":"\uac15\uc6d0","\uc2dc\uad70\uad6c":"\uac15\uc6d0\ub3c4 \ud6a1\uc131\uad70","\uae30\uad00":"\uc2e4\ub85c\uc554\ub178\uc778\ubcf5\uc9c0\uc13c\ud130","\uc8fc\uc18c":"\uac15\uc6d0 \ud6a1\uc131\uad70 \ud6a1\uc131\uc74d \uc55e\ub4e4\uc11c2\ub85c 76\uc2e4\ub85c\uc554\ub178\uc778\ubcf5\uc9c0\uc13c\ud130"},{"\uc9c0\uc5ed":"\uac15\uc6d0","\uc2dc\uad70\uad6c":"\uac15\uc6d0\ub3c4 \ud6a1\uc131\uad70","\uae30\uad00":"\ud6a1\uc131\uad70\ub178\uc778\uc804\ubb38\uc694\uc591\uc6d0","\uc8fc\uc18c":"\uac15\uc6d0\ub3c4 \ud6a1\uc131\uad70 \ud6a1\uc131\uc74d \ud6a1\uc131\ub85c 279(\uad6c, \uc785\uc11d\ub9ac 130-1), \ud6a1\uc131\uad70\ub178\uc778\uc804\ubb38\uc694\uc591\uc6d0"},{"\uc9c0\uc5ed":"\uac15\uc6d0","\uc2dc\uad70\uad6c":"\uac15\uc6d0\ub3c4 \ud6a1\uc131\uad70","\uae30\uad00":"\ud6a1\uc131\ub178\uc778\ubcf5\uc9c0\uc13c\ud130","\uc8fc\uc18c":"\uac15\uc6d0\ub3c4 \ud6a1\uc131\uad70 \ub454\ub0b4\ub85c93"},{"\uc9c0\uc5ed":"\uac15\uc6d0","\uc2dc\uad70\uad6c":"\uac15\uc6d0\ub3c4 \ud6a1\uc131\uad70","\uae30\uad00":"\ud6a1\uc131\uad70\uc7a5\uc560\uc778\ubcf4\ud638\uc791\uc5c5\uc7a5\ubcf4\ub78c\uc6d0","\uc8fc\uc18c":"\uac15\uc6d0 \ud6a1\uc131\uad70 \ud6a1\uc131\uc74d \ud559\uace1\ub9ac 470-1"},{"\uc9c0\uc5ed":"\uac15\uc6d0","\uc2dc\uad70\uad6c":"\uac15\uc6d0\ub3c4 \ud6a1\uc131\uad70","\uae30\uad00":"\ud6a1\uc131\uad70\uc885\ud569\uc0ac\ud68c\ubcf5\uc9c0\uad00","\uc8fc\uc18c":"\uac15\uc6d0\ub3c4 \ud6a1\uc131\uad70 \ud6a1\uc131\uc74d \ud6a1\uc131\ub85c379 \ud6a1\uc131\uad70\uc885\ud569\ubcf4\uac74\ubcf5\uc9c0\ud0c0\uc6b4 3\uce35 \ubcf5\uc9c0\uad00\uc0ac\ubb34\uc2e4"},{"\uc9c0\uc5ed":"\uac15\uc6d0","\uc2dc\uad70\uad6c":"\uac15\uc6d0\ub3c4 \ud6a1\uc131\uad70","\uae30\uad00":"\ud6a1\uc131\uad70\uc0ac\ud68c\ubcf5\uc9c0\ud611\uc758\ud68c","\uc8fc\uc18c":"\uac15\uc6d0\ub3c4 \ud6a1\uc131\uad70 \ud6a1\uc131\uc74d \uc5b4\uc218\ub85c 46\ud6a1\uc131\uad70\uc0ac\ud68c\ubcf5\uc9c0\ud611\uc758\ud68c\uad00"}]